bridgic/protocols/mcp/__init__.py
bridgic/protocols/mcp/_error.py
bridgic/protocols/mcp/_mcp_server_connection.py
bridgic/protocols/mcp/_mcp_server_connection_manager.py
bridgic/protocols/mcp/_mcp_template.py
bridgic/protocols/mcp/_mcp_tool_spec.py
bridgic/protocols/mcp/_mcp_tool_worker.py
bridgic_protocols_mcp-0.1.0.dist-info/METADATA
bridgic_protocols_mcp-0.1.0.dist-info/WHEEL
bridgic_protocols_mcp-0.1.0.dist-info/licenses/LICENSE
bridgic_protocols_mcp-0.1.0.dist-info/RECORD
