Metadata-Version: 2.4
Name: bridgic-protocols-mcp
Version: 0.1.0
Summary: Model Context Protocol (MCP) integration for Bridgic.
Author-email: Tielei Zhang <zhangtl04@gmail.com>
License: MIT
License-File: LICENSE
Classifier: Programming Language :: Python :: 3
Classifier: Programming Language :: Python :: 3.10
Classifier: Programming Language :: Python :: 3.11
Classifier: Programming Language :: Python :: 3.12
Classifier: Programming Language :: Python :: 3.13
Requires-Python: >=3.10
Requires-Dist: bridgic-core>=0.2.1
Requires-Dist: fastmcp>=2.13.0
Requires-Dist: mcp>=1.24.0
Requires-Dist: websockets>=15.0.1
